ansinv.py
ansinv-4.0.0.dist-info/LICENSE
ansinv-4.0.0.dist-info/METADATA
ansinv-4.0.0.dist-info/WHEEL
ansinv-4.0.0.dist-info/top_level.txt
ansinv-4.0.0.dist-info/RECORD
