Metadata-Version: 2.1
Name: ansinv
Version: 4.0.0
Summary: Generate Ansible Inventory
Home-page: https://github.com/rsjethani/ansinv
Author: Ravi Shekhar Jethani
Author-email: rsjethani@gmail.com
License: MIT
Project-URL: source, https://github.com/rsjethani/ansinv
Keywords: ansible devops
Platform: UNKNOWN
Classifier: Development Status :: 5 - Production/Stable
Classifier: Intended Audience :: Developers
Classifier: Topic :: Software Development :: Build Tools
Classifier: License :: OSI Approved :: MIT License
Classifier: Programming Language :: Python :: 2
Classifier: Programming Language :: Python :: 2.7
Classifier: Programming Language :: Python :: 3
Classifier: Programming Language :: Python :: 3.4
Classifier: Programming Language :: Python :: 3.5
Classifier: Programming Language :: Python :: 3.6
Classifier: Programming Language :: Python :: 3.7
